{
    "Index": 3,
    "Name": "Merkbee",
    "Face": 303,
    "Hair": 0,
    "Weapon": 0,
    "Health": 242,
    "Rotation": 153,
    "Level": 3,
    "Height": 3,
    "Chest": 119,
    "Leg": 119,
    "MobType": 1025,
    "SpawnType": 0,
    "IsService": 0,
    "Positions": [
        {
            "StartPosX": 3484,
            "StartPosY": 836,
            "StartRange": 6,
            "StartWait": 6,
            "DestPosX": 3493,
            "DestPosY": 836,
            "DestRange": 12,
            "DestWait": 5
        },
        {
            "StartPosX": 3496,
            "StartPosY": 836,
            "StartRange": 8,
            "StartWait": 6,
            "DestPosX": 3496,
            "DestPosY": 841,
            "DestRange": 11,
            "DestWait": 5
        },
        {
            "StartPosX": 3498,
            "StartPosY": 827,
            "StartRange": 6,
            "StartWait": 5,
            "DestPosX": 3490,
            "DestPosY": 838,
            "DestRange": 8,
            "DestWait": 4
        },
        {
            "StartPosX": 3511,
            "StartPosY": 840,
            "StartRange": 6,
            "StartWait": 6,
            "DestPosX": 3504,
            "DestPosY": 849,
            "DestRange": 12,
            "DestWait": 6
        },
        {
            "StartPosX": 3518,
            "StartPosY": 848,
            "StartRange": 6,
            "StartWait": 8,
            "DestPosX": 3528,
            "DestPosY": 840,
            "DestRange": 8,
            "DestWait": 8
        },
        {
            "StartPosX": 3523,
            "StartPosY": 837,
            "StartRange": 12,
            "StartWait": 7,
            "DestPosX": 3519,
            "DestPosY": 832,
            "DestRange": 7,
            "DestWait": 4
        },
        {
            "StartPosX": 3515,
            "StartPosY": 827,
            "StartRange": 7,
            "StartWait": 7,
            "DestPosX": 3516,
            "DestPosY": 815,
            "DestRange": 10,
            "DestWait": 6
        },
        {
            "StartPosX": 3525,
            "StartPosY": 845,
            "StartRange": 9,
            "StartWait": 5,
            "DestPosX": 3513,
            "DestPosY": 849,
            "DestRange": 10,
            "DestWait": 4
        },
        {
            "StartPosX": 3494,
            "StartPosY": 863,
            "StartRange": 7,
            "StartWait": 4,
            "DestPosX": 3491,
            "DestPosY": 852,
            "DestRange": 7,
            "DestWait": 7
        },
        {
            "StartPosX": 3499,
            "StartPosY": 867,
            "StartRange": 7,
            "StartWait": 7,
            "DestPosX": 3488,
            "DestPosY": 859,
            "DestRange": 12,
            "DestWait": 8
        },
        {
            "StartPosX": 3510,
            "StartPosY": 884,
            "StartRange": 12,
            "StartWait": 8,
            "DestPosX": 3516,
            "DestPosY": 878,
            "DestRange": 11,
            "DestWait": 4
        },
        {
            "StartPosX": 3514,
            "StartPosY": 864,
            "StartRange": 10,
            "StartWait": 7,
            "DestPosX": 3502,
            "DestPosY": 858,
            "DestRange": 6,
            "DestWait": 5
        },
        {
            "StartPosX": 3521,
            "StartPosY": 863,
            "StartRange": 9,
            "StartWait": 4,
            "DestPosX": 3521,
            "DestPosY": 868,
            "DestRange": 9,
            "DestWait": 6
        },
        {
            "StartPosX": 3524,
            "StartPosY": 880,
            "StartRange": 11,
            "StartWait": 7,
            "DestPosX": 3530,
            "DestPosY": 870,
            "DestRange": 8,
            "DestWait": 7
        },
        {
            "StartPosX": 3532,
            "StartPosY": 880,
            "StartRange": 8,
            "StartWait": 7,
            "DestPosX": 3542,
            "DestPosY": 868,
            "DestRange": 7,
            "DestWait": 4
        },
        {
            "StartPosX": 3429,
            "StartPosY": 875,
            "StartRange": 8,
            "StartWait": 6,
            "DestPosX": 3437,
            "DestPosY": 875,
            "DestRange": 8,
            "DestWait": 5
        },
        {
            "StartPosX": 3436,
            "StartPosY": 867,
            "StartRange": 12,
            "StartWait": 7,
            "DestPosX": 3439,
            "DestPosY": 865,
            "DestRange": 8,
            "DestWait": 8
        },
        {
            "StartPosX": 3437,
            "StartPosY": 858,
            "StartRange": 12,
            "StartWait": 4,
            "DestPosX": 3439,
            "DestPosY": 849,
            "DestRange": 9,
            "DestWait": 4
        },
        {
            "StartPosX": 3421,
            "StartPosY": 876,
            "StartRange": 7,
            "StartWait": 7,
            "DestPosX": 3418,
            "DestPosY": 874,
            "DestRange": 12,
            "DestWait": 4
        },
        {
            "StartPosX": 3437,
            "StartPosY": 891,
            "StartRange": 7,
            "StartWait": 5,
            "DestPosX": 3429,
            "DestPosY": 882,
            "DestRange": 9,
            "DestWait": 7
        },
        {
            "StartPosX": 3422,
            "StartPosY": 842,
            "StartRange": 10,
            "StartWait": 6,
            "DestPosX": 3416,
            "DestPosY": 854,
            "DestRange": 10,
            "DestWait": 6
        },
        {
            "StartPosX": 3413,
            "StartPosY": 846,
            "StartRange": 12,
            "StartWait": 5,
            "DestPosX": 3416,
            "DestPosY": 838,
            "DestRange": 8,
            "DestWait": 8
        },
        {
            "StartPosX": 3423,
            "StartPosY": 849,
            "StartRange": 6,
            "StartWait": 6,
            "DestPosX": 3419,
            "DestPosY": 852,
            "DestRange": 8,
            "DestWait": 6
        },
        {
            "StartPosX": 3423,
            "StartPosY": 867,
            "StartRange": 7,
            "StartWait": 5,
            "DestPosX": 3420,
            "DestPosY": 872,
            "DestRange": 9,
            "DestWait": 7
        },
        {
            "StartPosX": 3492,
            "StartPosY": 1003,
            "StartRange": 12,
            "StartWait": 8,
            "DestPosX": 3491,
            "DestPosY": 991,
            "DestRange": 6,
            "DestWait": 4
        },
        {
            "StartPosX": 3496,
            "StartPosY": 1008,
            "StartRange": 7,
            "StartWait": 6,
            "DestPosX": 3487,
            "DestPosY": 1000,
            "DestRange": 10,
            "DestWait": 7
        },
        {
            "StartPosX": 3499,
            "StartPosY": 1015,
            "StartRange": 7,
            "StartWait": 7,
            "DestPosX": 3508,
            "DestPosY": 1013,
            "DestRange": 6,
            "DestWait": 4
        },
        {
            "StartPosX": 3507,
            "StartPosY": 971,
            "StartRange": 11,
            "StartWait": 6,
            "DestPosX": 3508,
            "DestPosY": 978,
            "DestRange": 9,
            "DestWait": 8
        },
        {
            "StartPosX": 3407,
            "StartPosY": 959,
            "StartRange": 9,
            "StartWait": 6,
            "DestPosX": 3400,
            "DestPosY": 947,
            "DestRange": 11,
            "DestWait": 8
        },
        {
            "StartPosX": 3408,
            "StartPosY": 954,
            "StartRange": 8,
            "StartWait": 6,
            "DestPosX": 3418,
            "DestPosY": 965,
            "DestRange": 10,
            "DestWait": 7
        },
        {
            "StartPosX": 3415,
            "StartPosY": 954,
            "StartRange": 9,
            "StartWait": 8,
            "DestPosX": 3403,
            "DestPosY": 955,
            "DestRange": 12,
            "DestWait": 6
        },
        {
            "StartPosX": 3575,
            "StartPosY": 908,
            "StartRange": 10,
            "StartWait": 7,
            "DestPosX": 3575,
            "DestPosY": 915,
            "DestRange": 6,
            "DestWait": 4
        },
        {
            "StartPosX": 3452,
            "StartPosY": 992,
            "StartRange": 8,
            "StartWait": 8,
            "DestPosX": 3455,
            "DestPosY": 995,
            "DestRange": 11,
            "DestWait": 7
        },
        {
            "StartPosX": 3453,
            "StartPosY": 976,
            "StartRange": 9,
            "StartWait": 4,
            "DestPosX": 3464,
            "DestPosY": 965,
            "DestRange": 12,
            "DestWait": 6
        },
        {
            "StartPosX": 3455,
            "StartPosY": 985,
            "StartRange": 12,
            "StartWait": 6,
            "DestPosX": 3456,
            "DestPosY": 993,
            "DestRange": 10,
            "DestWait": 7
        },
        {
            "StartPosX": 3510,
            "StartPosY": 977,
            "StartRange": 9,
            "StartWait": 6,
            "DestPosX": 3517,
            "DestPosY": 965,
            "DestRange": 7,
            "DestWait": 4
        },
        {
            "StartPosX": 3513,
            "StartPosY": 969,
            "StartRange": 6,
            "StartWait": 7,
            "DestPosX": 3514,
            "DestPosY": 979,
            "DestRange": 9,
            "DestWait": 6
        },
        {
            "StartPosX": 3584,
            "StartPosY": 865,
            "StartRange": 8,
            "StartWait": 7,
            "DestPosX": 3578,
            "DestPosY": 877,
            "DestRange": 12,
            "DestWait": 6
        },
        {
            "StartPosX": 3599,
            "StartPosY": 867,
            "StartRange": 12,
            "StartWait": 4,
            "DestPosX": 3595,
            "DestPosY": 876,
            "DestRange": 7,
            "DestWait": 7
        },
        {
            "StartPosX": 3625,
            "StartPosY": 937,
            "StartRange": 12,
            "StartWait": 4,
            "DestPosX": 3631,
            "DestPosY": 949,
            "DestRange": 9,
            "DestWait": 4
        },
        {
            "StartPosX": 3633,
            "StartPosY": 932,
            "StartRange": 12,
            "StartWait": 6,
            "DestPosX": 3629,
            "DestPosY": 931,
            "DestRange": 9,
            "DestWait": 5
        },
        {
            "StartPosX": 3599,
            "StartPosY": 953,
            "StartRange": 8,
            "StartWait": 7,
            "DestPosX": 3591,
            "DestPosY": 944,
            "DestRange": 9,
            "DestWait": 7
        },
        {
            "StartPosX": 3603,
            "StartPosY": 957,
            "StartRange": 7,
            "StartWait": 8,
            "DestPosX": 3607,
            "DestPosY": 952,
            "DestRange": 8,
            "DestWait": 4
        },
        {
            "StartPosX": 3606,
            "StartPosY": 970,
            "StartRange": 7,
            "StartWait": 5,
            "DestPosX": 3594,
            "DestPosY": 969,
            "DestRange": 12,
            "DestWait": 5
        },
        {
            "StartPosX": 3683,
            "StartPosY": 891,
            "StartRange": 8,
            "StartWait": 5,
            "DestPosX": 3686,
            "DestPosY": 888,
            "DestRange": 8,
            "DestWait": 6
        },
        {
            "StartPosX": 3686,
            "StartPosY": 888,
            "StartRange": 10,
            "StartWait": 7,
            "DestPosX": 3695,
            "DestPosY": 893,
            "DestRange": 9,
            "DestWait": 6
        },
        {
            "StartPosX": 3608,
            "StartPosY": 959,
            "StartRange": 6,
            "StartWait": 5,
            "DestPosX": 3600,
            "DestPosY": 970,
            "DestRange": 7,
            "DestWait": 4
        },
        {
            "StartPosX": 3648,
            "StartPosY": 955,
            "StartRange": 10,
            "StartWait": 6,
            "DestPosX": 3654,
            "DestPosY": 943,
            "DestRange": 9,
            "DestWait": 5
        },
        {
            "StartPosX": 3605,
            "StartPosY": 870,
            "StartRange": 7,
            "StartWait": 5,
            "DestPosX": 3612,
            "DestPosY": 872,
            "DestRange": 9,
            "DestWait": 6
        }
    ]
}