{
    "Index": 2210,
    "Name": "847",
    "Description": "Mid-Ranking Aitan",
    "MobEffect": 0,
    "InitialDialog": 0,
    "Emote": 0,
    "Effect1": 0,
    "Effect2": 0,
    "Effect3": 0,
    "Effect4": 0,
    "WeaponGlow": 0,
    "Rotation": 0,
    "Sizes": {
        "Height": 7,
        "UpperBody": 119,
        "Leg": 119,
        "Body": 175
    },
    "Position": [
        2598.39990234375,
        1967.40002441406
    ],
    "Equip": [
        44,
        7706,
        2024,
        2054,
        2084,
        2114,
        1509,
        0
    ],
    "Inventory": [
        0,
        0,
        0,
        0,
        0,
        0,
        0,
        0,
        0,
        0,
        0,
        0,
        0,
        0,
        0,
        0,
        0,
        0,
        0,
        0,
        0,
        0,
        0,
        0,
        0,
        0,
        0,
        0,
        0,
        0,
        0,
        0,
        0,
        0,
        0,
        0,
        0,
        0,
        0,
        0
    ],
    "options": [
        {
            "text": "Nothing_1",
            "type": 12,
            "color": "0xFFFFFFFF"
        },
        {
            "text": "Missao",
            "type": 2,
            "color": "0xFFFFFFFF"
        }
    ]
}
